{"collectionName":"PIC.WH.CodeList","version":1781083496028,"updatedAt":"2026-06-10T09:24:56.028Z","lookupKeyField":"担当者","fields":["担当者","倉庫コード","明細倉庫コード"],"records":[{"id":"51","documentId":"51","baseDocumentId":"51","createdAt":{"_seconds":1780997407,"_nanoseconds":547000000},"倉庫コード":"30151","明細倉庫コード":"30151","担当者":"51","updatedAt":{"_seconds":1780997407,"_nanoseconds":547000000}},{"id":"52","documentId":"52","baseDocumentId":"52","createdAt":{"_seconds":1780997407,"_nanoseconds":547000000},"倉庫コード":"abc","明細倉庫コード":"def","担当者":"52","updatedAt":{"_seconds":1780997407,"_nanoseconds":547000000}}]}